odoo8_addon_product_pricelist_fixed_price-8.0.1.0.1.99.dev21-py2.7-nspkg.pth
odoo8_addon_product_pricelist_fixed_price-8.0.1.0.1.99.dev21.dist-info/METADATA
odoo8_addon_product_pricelist_fixed_price-8.0.1.0.1.99.dev21.dist-info/RECORD
odoo8_addon_product_pricelist_fixed_price-8.0.1.0.1.99.dev21.dist-info/WHEEL
odoo8_addon_product_pricelist_fixed_price-8.0.1.0.1.99.dev21.dist-info/namespace_packages.txt
odoo8_addon_product_pricelist_fixed_price-8.0.1.0.1.99.dev21.dist-info/top_level.txt
odoo_addons/product_pricelist_fixed_price/README.rst
odoo_addons/product_pricelist_fixed_price/__init__.py
odoo_addons/product_pricelist_fixed_price/__openerp__.py
odoo_addons/product_pricelist_fixed_price/init_hook.py
odoo_addons/product_pricelist_fixed_price/i18n/ca.po
odoo_addons/product_pricelist_fixed_price/i18n/de.po
odoo_addons/product_pricelist_fixed_price/i18n/es.po
odoo_addons/product_pricelist_fixed_price/i18n/fr.po
odoo_addons/product_pricelist_fixed_price/i18n/it.po
odoo_addons/product_pricelist_fixed_price/i18n/product_pricelist_fixed_price.pot
odoo_addons/product_pricelist_fixed_price/i18n/sl.po
odoo_addons/product_pricelist_fixed_price/model/__init__.py
odoo_addons/product_pricelist_fixed_price/model/product_pricelist_item.py
odoo_addons/product_pricelist_fixed_price/static/description/icon.png
odoo_addons/product_pricelist_fixed_price/tests/__init__.py
odoo_addons/product_pricelist_fixed_price/tests/test_product_pricelist_fixed_price.py
odoo_addons/product_pricelist_fixed_price/view/product_pricelist_item_view.xml
